ssh_keygen/__init__.py
ssh_keygen/__main__.py
ssh_keygen/balloon.py
ssh_keygen/ed25519.py
ssh_keygen/keygen.py
ssh_keygen-1.0.4.dist-info/licenses/LICENSE
ssh_keygen-1.0.4.dist-info/METADATA
ssh_keygen-1.0.4.dist-info/WHEEL
ssh_keygen-1.0.4.dist-info/top_level.txt
ssh_keygen-1.0.4.dist-info/RECORD
