Metadata-Version: 2.4
Name: ssh-keygen
Version: 1.0.4
Summary: ssh-keygen in pure python with seeded key generation support
Author-email: John Ao <johnao73thu@gmail.com>
License: Copyright (c) 2024 John Ao
Project-URL: Homepage, https://github.com/John-Ao/python-ssh-keygen
Keywords: ssh,key,generation
Classifier: License :: OSI Approved :: MIT License
Classifier: Programming Language :: Python
Classifier: Programming Language :: Python :: 3
Requires-Python: >=3.0
License-File: LICENSE
Requires-Dist: tqdm
Dynamic: license-file
